quantzoo/__init__.py
quantzoo/data.py
quantzoo/quantzoo.py
quantzoo/viz.py
quantzoo/clis/README.md
quantzoo/clis/__init__.py
quantzoo/clis/cli.py
quantzoo/strategies/__init__.py
quantzoo-2022.6.2.16.3.25.dist-info/AUTHORS.rst
quantzoo-2022.6.2.16.3.25.dist-info/LICENSE
quantzoo-2022.6.2.16.3.25.dist-info/METADATA
quantzoo-2022.6.2.16.3.25.dist-info/WHEEL
quantzoo-2022.6.2.16.3.25.dist-info/entry_points.txt
quantzoo-2022.6.2.16.3.25.dist-info/top_level.txt
quantzoo-2022.6.2.16.3.25.dist-info/RECORD
