Metadata-Version: 2.1
Name: quantzoo
Version: 2022.6.2.16.3.25
Summary: Create a Python package.
Home-page: https://github.com/Jie-Yuan/quantzoo
Author: Betterme
Author-email: yuanjie@huatai.com
License: MIT license
Keywords: quantzoo
Platform: UNKNOWN
Classifier: Development Status :: 2 - Pre-Alpha
Classifier: Intended Audience :: Developers
Classifier: License :: OSI Approved :: MIT License
Classifier: Natural Language :: English
Classifier: Programming Language :: Python :: 3
Classifier: Programming Language :: Python :: 3.6
Classifier: Programming Language :: Python :: 3.7
Classifier: Programming Language :: Python :: 3.8
Requires-Python: >=3.6
License-File: LICENSE
License-File: AUTHORS.rst
Requires-Dist: meutils
Requires-Dist: akshare
Requires-Dist: pypinyin
